[
    {
        "date": "2015-02-01",
        "Value": 22575.9
    },
    {
        "date": "2015-03-01",
        "Value": 23332.28
    },
    {
        "date": "2015-04-01",
        "Value": 23841.94
    },
    {
        "date": "2015-05-01",
        "Value": 24171.68
    },
    {
        "date": "2015-06-01",
        "Value": 24081.61
    },
    {
        "date": "2015-07-01",
        "Value": 23758.8
    },
    {
        "date": "2015-08-01",
        "Value": 23820.0
    },
    {
        "date": "2015-09-01",
        "Value": 24017.87
    },
    {
        "date": "2015-10-01",
        "Value": 24207.66
    },
    {
        "date": "2015-11-01",
        "Value": 24784.09
    },
    {
        "date": "2015-12-01",
        "Value": 24976.16
    },
    {
        "date": "2016-01-01",
        "Value": 25010.53
    },
    {
        "date": "2016-02-01",
        "Value": 25479.06
    },
    {
        "date": "2016-03-01",
        "Value": 26585.58
    },
    {
        "date": "2016-04-01",
        "Value": 28509.57
    },
    {
        "date": "2016-05-01",
        "Value": 27021.6
    },
    {
        "date": "2016-06-01",
        "Value": 27231.89
    },
    {
        "date": "2016-07-01",
        "Value": 27222.86
    },
    {
        "date": "2016-08-01",
        "Value": 27638.8
    },
    {
        "date": "2016-09-01",
        "Value": 29134.5
    },
    {
        "date": "2016-10-01",
        "Value": 28399.42
    },
    {
        "date": "2016-11-01",
        "Value": 26951.11
    },
    {
        "date": "2016-12-01",
        "Value": 20657.98
    },
    {
        "date": "2017-01-01",
        "Value": 20935.37
    },
    {
        "date": "2017-02-01",
        "Value": 22546.5
    },
    {
        "date": "2017-03-01",
        "Value": 24161.72
    },
    {
        "date": "2017-04-01",
        "Value": 26537.73
    },
    {
        "date": "2017-05-01",
        "Value": 27373.59
    },
    {
        "date": "2017-06-01",
        "Value": 27988.43
    },
    {
        "date": "2017-07-01",
        "Value": 27846.47
    },
    {
        "date": "2017-08-01",
        "Value": 28286.73
    },
    {
        "date": "2017-09-01",
        "Value": 28225.84
    },
    {
        "date": "2017-10-01",
        "Value": 29069.06
    },
    {
        "date": "2017-11-01",
        "Value": 29288.32
    },
    {
        "date": "2017-12-01",
        "Value": 29600.91
    },
    {
        "date": "2018-01-01",
        "Value": 29918.35
    },
    {
        "date": "2018-02-01",
        "Value": 30479.17
    },
    {
        "date": "2018-03-01",
        "Value": 31201.67
    },
    {
        "date": "2018-04-01",
        "Value": 32378.01
    },
    {
        "date": "2018-05-01",
        "Value": 32636.44
    },
    {
        "date": "2018-06-01",
        "Value": 32739.15
    },
    {
        "date": "2018-07-01",
        "Value": 32897.08
    },
    {
        "date": "2018-08-01",
        "Value": 32980.7
    },
    {
        "date": "2018-09-01",
        "Value": 33059.67
    },
    {
        "date": "2018-10-01",
        "Value": 33429.66
    },
    {
        "date": "2018-11-01",
        "Value": 34142.16
    },
    {
        "date": "2018-12-01",
        "Value": 34041.59
    },
    {
        "date": "2019-01-01",
        "Value": 34510.22
    },
    {
        "date": "2019-02-01",
        "Value": 34936.98
    },
    {
        "date": "2019-03-01",
        "Value": 35970.22
    },
    {
        "date": "2019-04-01",
        "Value": 37403.94
    },
    {
        "date": "2019-05-01",
        "Value": 37067.55
    },
    {
        "date": "2019-06-01",
        "Value": 37042.18
    },
    {
        "date": "2019-07-01",
        "Value": 37153.85
    },
    {
        "date": "2019-08-01",
        "Value": 36941.69
    },
    {
        "date": "2019-09-01",
        "Value": 37901.24
    },
    {
        "date": "2019-10-01",
        "Value": 37595.44
    },
    {
        "date": "2019-11-01",
        "Value": 37911.49
    },
    {
        "date": "2019-12-01",
        "Value": 38580.3
    },
    {
        "date": "2020-01-01",
        "Value": 38404.38
    },
    {
        "date": "2020-02-01",
        "Value": 39146.9
    },
    {
        "date": "2020-03-01",
        "Value": 40623.07
    },
    {
        "date": "2020-04-01",
        "Value": 41744.58
    },
    {
        "date": "2020-05-01",
        "Value": 42339.37
    },
    {
        "date": "2020-06-01",
        "Value": 43309.74
    },
    {
        "date": "2020-07-01",
        "Value": 43848.99
    },
    {
        "date": "2020-08-01",
        "Value": 43593.28
    },
    {
        "date": "2020-09-01",
        "Value": 44227.84
    },
    {
        "date": "2020-10-01",
        "Value": 43847.63
    },
    {
        "date": "2020-11-01",
        "Value": 44427.03
    },
    {
        "date": "2020-12-01",
        "Value": 45923.67
    },
    {
        "date": "2021-01-01",
        "Value": 46127.69
    },
    {
        "date": "2021-02-01",
        "Value": 47554.2
    },
    {
        "date": "2021-03-01",
        "Value": 49403.26
    },
    {
        "date": "2021-04-01",
        "Value": 48513.34
    },
    {
        "date": "2021-05-01",
        "Value": 48827.66
    },
    {
        "date": "2021-06-01",
        "Value": 49437.5
    },
    {
        "date": "2021-07-01",
        "Value": 49616.69
    },
    {
        "date": "2021-08-01",
        "Value": 49810.93
    },
    {
        "date": "2021-09-01",
        "Value": 49481.73
    },
    {
        "date": "2021-10-01",
        "Value": 49691.54
    },
    {
        "date": "2021-11-01",
        "Value": 52067.42
    },
    {
        "date": "2021-12-01",
        "Value": 51011.58
    },
    {
        "date": "2022-01-01",
        "Value": 51209.39
    },
    {
        "date": "2022-02-01",
        "Value": 52307.17
    },
    {
        "date": "2022-03-01",
        "Value": 52856.6
    },
    {
        "date": "2022-04-01",
        "Value": 54717.61
    },
    {
        "date": "2022-05-01",
        "Value": 55050.03
    },
    {
        "date": "2022-06-01",
        "Value": 54622.68
    },
    {
        "date": "2022-07-01",
        "Value": 55150.14
    },
    {
        "date": "2022-08-01",
        "Value": 54705.61
    },
    {
        "date": "2022-09-01",
        "Value": 54312.47
    },
    {
        "date": "2022-10-01",
        "Value": 55296.41
    },
    {
        "date": "2022-11-01",
        "Value": 55439.13
    },
    {
        "date": "2022-12-01",
        "Value": 55710.46
    },
    {
        "date": "2023-01-01",
        "Value": 56383.57
    },
    {
        "date": "2023-02-01",
        "Value": 57876.21
    },
    {
        "date": "2023-03-01",
        "Value": 57803.09
    },
    {
        "date": "2023-04-01",
        "Value": 58962.14
    },
    {
        "date": "2023-05-01",
        "Value": 59005.44
    },
    {
        "date": "2023-06-01",
        "Value": 61037.92
    },
    {
        "date": "2023-07-01",
        "Value": 58853.61
    },
    {
        "date": "2023-08-01",
        "Value": 58288.02
    },
    {
        "date": "2023-09-01",
        "Value": 58131.05
    },
    {
        "date": "2023-10-01",
        "Value": 58684.6
    },
    {
        "date": "2023-11-01",
        "Value": 59775.72
    },
    {
        "date": "2023-12-01",
        "Value": 61174.78
    },
    {
        "date": "2024-01-01",
        "Value": 61017.6
    },
    {
        "date": "2024-02-01",
        "Value": 61560.26
    },
    {
        "date": "2024-03-01",
        "Value": 61855.49
    },
    {
        "date": "2024-04-01",
        "Value": 63430.26
    },
    {
        "date": "2024-05-01",
        "Value": 64113.7
    },
    {
        "date": "2024-06-01",
        "Value": 65139.84
    },
    {
        "date": "2024-07-01",
        "Value": 63306.53
    },
    {
        "date": "2024-08-01",
        "Value": 63109.73
    },
    {
        "date": "2024-09-01",
        "Value": 63263.7
    },
    {
        "date": "2024-10-01",
        "Value": 64005.27
    },
    {
        "date": "2024-11-01",
        "Value": 64667.35
    },
    {
        "date": "2024-12-01",
        "Value": 64732.07
    },
    {
        "date": "2025-01-01",
        "Value": 64604.97
    }
]